build/lib/build/lib/build/lib/build/lib/build/lib/build/lib/build/lib/build/lib/build/lib/build/lib/env/bin/rst2html.py
build/lib/build/lib/build/lib/build/lib/build/lib/build/lib/build/lib/build/lib/build/lib/build/lib/env/bin/rst2html4.py
build/lib/build/lib/build/lib/build/lib/build/lib/build/lib/build/lib/build/lib/build/lib/build/lib/env/bin/rst2html5.py
build/lib/build/lib/build/lib/build/lib/build/lib/build/lib/build/lib/build/lib/build/lib/build/lib/env/bin/rst2latex.py
build/lib/build/lib/build/lib/build/lib/build/lib/build/lib/build/lib/build/lib/build/lib/build/lib/env/bin/rst2man.py
build/lib/build/lib/build/lib/build/lib/build/lib/build/lib/build/lib/build/lib/build/lib/build/lib/env/bin/rst2odt.py
build/lib/build/lib/build/lib/build/lib/build/lib/build/lib/build/lib/build/lib/build/lib/build/lib/env/bin/rst2odt_prepstyles.py
build/lib/build/lib/build/lib/build/lib/build/lib/build/lib/build/lib/build/lib/build/lib/build/lib/env/bin/rst2pseudoxml.py
build/lib/build/lib/build/lib/build/lib/build/lib/build/lib/build/lib/build/lib/build/lib/build/lib/env/bin/rst2s5.py
build/lib/build/lib/build/lib/build/lib/build/lib/build/lib/build/lib/build/lib/build/lib/build/lib/env/bin/rst2xetex.py
build/lib/build/lib/build/lib/build/lib/build/lib/build/lib/build/lib/build/lib/build/lib/build/lib/env/bin/rst2xml.py
build/lib/build/lib/build/lib/build/lib/build/lib/build/lib/build/lib/build/lib/build/lib/build/lib/env/bin/rstpep2html.py
build/lib/build/lib/build/lib/build/lib/build/lib/build/lib/build/lib/build/lib/build/lib/build/lib/siafi/__init__.py
build/lib/build/lib/build/lib/build/lib/build/lib/build/lib/build/lib/build/lib/build/lib/build/lib/siafi/hooks/__init__.py
build/lib/build/lib/build/lib/build/lib/build/lib/build/lib/build/lib/build/lib/build/lib/build/lib/siafi/hooks/siafi.py
build/lib/build/lib/build/lib/build/lib/build/lib/build/lib/build/lib/build/lib/build/lib/eb/airflow/providers/siafi/__init__.py
eb_airflow_providers_siafi-1.2.0.dist-info/LICENSE.txt
eb_airflow_providers_siafi-1.2.0.dist-info/METADATA
eb_airflow_providers_siafi-1.2.0.dist-info/WHEEL
eb_airflow_providers_siafi-1.2.0.dist-info/entry_points.txt
eb_airflow_providers_siafi-1.2.0.dist-info/top_level.txt
eb_airflow_providers_siafi-1.2.0.dist-info/RECORD
