Metadata-Version: 2.1
Name: eb-airflow-providers-siafi
Version: 1.2.0
Summary: Provider para interações com o SIAFI e seus sistemas derivados
Home-page: UNKNOWN
Author: Carlos Alberto Duarte Pinto
Author-email: carlos.adpinto@gmail.com
License: Exército Brasileiro
Keywords: airflow,siafi,administracao,governo
Platform: UNKNOWN
Requires-Dist: apache-airflow
